setup.py
tenkishocho/__init__.py
tenkishocho/tenkishocho.py
tenkishocho/tenkishocho_test.py
tenkishocho.egg-info/PKG-INFO
tenkishocho.egg-info/SOURCES.txt
tenkishocho.egg-info/dependency_links.txt
tenkishocho.egg-info/top_level.txt