Metadata-Version: 1.0
Name: tenkishocho
Version: 0.0.5
Summary: Japan Weather API from KISHOCHO WEB SYSTEM
Home-page: UNKNOWN
Author: Shintaro Ikeda
Author-email: ikenshirogivenup98@gmail.com
License: MIT
Platform: UNKNOWN
